MANIFEST.in
README
setup.py
WeBIAS.egg-info/PKG-INFO
WeBIAS.egg-info/SOURCES.txt
WeBIAS.egg-info/dependency_links.txt
WeBIAS.egg-info/entry_points.txt
WeBIAS.egg-info/requires.txt
WeBIAS.egg-info/top_level.txt
webias/__init__.py
webias/admin.py
webias/application.py
webias/auth.py
webias/biodb.py
webias/biofield.py
webias/config.py
webias/console.py
webias/data.py
webias/field.py
webias/query.py
webias/reports.py
webias/statistics.py
webias/template.py
webias/user.py
webias/util.py
webias/data/runner.py
webias/data/conf/config.ini.sample
webias/data/examples/apps/groups.xml
webias/data/examples/apps/server_map.xml
webias/data/examples/apps/test.xml
webias/data/examples/apps/vargroups.xml
webias/data/examples/programs/test.py
webias/data/examples/templates/examples/Test/param_table.genshi
webias/data/examples/templates/page/example.genshi
webias/data/examples/templates/page/Test/help.genshi
webias/data/media/WeBIAS.css
webias/data/media/WeBIAS.js
webias/data/media/form.css
webias/data/media/help.png
webias/data/media/jquery-1.8.2.js
webias/data/media/jquery-1.8.2.min.js
webias/data/media/jquery-ui-1.8.23.custom.css
webias/data/media/jquery-ui-1.8.23.custom.min.js
webias/data/media/jquery-ui.css
webias/data/media/jquery-ui.js
webias/data/media/jquery.form.js
webias/data/media/jquery.js
webias/data/media/loader.gif
webias/data/media/star_grey.png
webias/data/media/star_yellow.png
webias/data/media/images/ui-bg_flat_0_aaaaaa_40x100.png
webias/data/media/images/ui-bg_flat_75_ffffff_40x100.png
webias/data/media/images/ui-bg_glass_55_fbf9ee_1x400.png
webias/data/media/images/ui-bg_glass_65_ffffff_1x400.png
webias/data/media/images/ui-bg_glass_75_dadada_1x400.png
webias/data/media/images/ui-bg_glass_75_e6e6e6_1x400.png
webias/data/media/images/ui-bg_glass_95_fef1ec_1x400.png
webias/data/media/images/ui-bg_highlight-soft_75_cccccc_1x100.png
webias/data/media/images/ui-icons_222222_256x240.png
webias/data/media/images/ui-icons_2e83ff_256x240.png
webias/data/media/images/ui-icons_454545_256x240.png
webias/data/media/images/ui-icons_888888_256x240.png
webias/data/media/images/ui-icons_cd0a0a_256x240.png
webias/data/templates/system/app_list.genshi
