Metadata-Version: 1.0
Name: WeBIAS
Version: 1.0.1
Summary: WeBIAS is a web server for publishing services. A service is a standalone command line program, which has to be supplied with certain parameters, and its output should be returned. Computations may require significant resources and time, and may have to be scheduled for later execution. Users are informed when their requests are finished and can peruse results at their convenience.
Home-page: http://bioinfo.imdik.pan.pl/webias
Author: Pawel Daniluk
Author-email: pawel@bioexploratorium.pl
License: AGPL
Platform: UNKNOWN
